localres.py
localres-1.7.dist-info/LICENSE
localres-1.7.dist-info/METADATA
localres-1.7.dist-info/WHEEL
localres-1.7.dist-info/entry_points.txt
localres-1.7.dist-info/top_level.txt
localres-1.7.dist-info/RECORD
