Metadata-Version: 2.1
Name: localres
Version: 1.7
Summary: Plot the histogram of local resolution values of a cryo-EM reconstruction
Home-page: https://github.com/Guillawme/localres
Author: Guillaume Gaullier
Author-email: contact@gaullier.org
License: UNKNOWN
Project-URL: Bug Reports, https://github.com/Guillawme/localres/issues
Project-URL: Source, https://github.com/Guillawme/localres
Keywords: cryo-EM map local resolution histogram visualization
Platform: UNKNOWN
Classifier: Development Status :: 5 - Production/Stable
Classifier: Intended Audience :: Science/Research
Classifier: Topic :: Scientific/Engineering
Classifier: Topic :: Scientific/Engineering :: Bio-Informatics
Classifier: Topic :: Scientific/Engineering :: Visualization
Classifier: License :: OSI Approved :: MIT License
Classifier: Programming Language :: Python :: 3
Classifier: Operating System :: OS Independent
Classifier: Environment :: Console
Classifier: Natural Language :: English
Requires-Python: >=3.9.7
License-File: LICENSE
Requires-Dist: click (>=8.0.3)
Requires-Dist: matplotlib (>=3.4.3)
Requires-Dist: mrcfile (>=1.3.0)
Requires-Dist: numpy (>=1.21.2)
